vlsi-noor/lab3-dff-tff-shiftreg-counter/tff.v
module tff(t,clk,reset,q);
input t, clk, reset;
output q;
reg q;


always@(posedge clk or posedge reset)
	if(t)
		q <= ~q;
    else if(reset)
        q <= 1'b0;
    else
        q <= q;

endmodule

vlsi-noor/lab3-dff-tff-shiftreg-counter/updowncounter.v
`include "tff.v"
module sync_updown(a,t,clock,reset,q);
input t,clock, reset;
input a;
output [3:0]q;

wire x0,x1,x2;
tff T0(t,clock, reset,q[0]);

assign x0=(q[0]&a)|(~q[0]&~a);
tff T1(x0,clock, reset,q[1]);

assign x1=(q[1]&q[0]&a)|(~q[0]&~a&~q[1]);
tff T2(x1,clock, reset,q[2]);

assign x2=(q[2]&q[1]&q[0]&a)|(~q[0]&~a&~q[1]&~q[2]);
tff T3(x2,clock, reset,q[3]);
endmodule

vlsi-noor/lab3-dff-tff-shiftreg-counter/updowncounter_tb.v
// `include "updowncounter.v"

module updowncounter_tb;
reg clk,reset;
wire [3:0]q;

reg a;
reg t;
initial
begin
	$dumpfile("updowncounter_tb.vcd");
	$dumpvars(0,updowncounter_tb);
end

sync_updown u1(a,t,clk,reset,q);


initial
begin
a=1;
clk =0;
t=1;
reset=1;
#5 reset=0;
// after 145 unit time 
#145 a=0;
end

always 
#5  clk =  ! clk; 



always@(q)
	begin
 		$display($time ," clk=%b, rst=%b,q=%b\n", clk, reset, q);
	end 

initial

	#300 $finish;
endmodule

vlsi-noor/lab3-dff-tff-shiftreg-counter/updowncounter_tb.vcd
$date
	Fri Aug 30 15:39:45 2019
$end
$version
	Icarus Verilog
$end
$timescale
	1s
$end
$scope module updowncounter_tb $end
$var wire 4 ! q [3:0] $end
$var reg 1 " a $end
$var reg 1 # clk $end
$var reg 1 $ reset $end
$var reg 1 % t $end
$scope module u1 $end
$var wire 1 " a $end
$var wire 1 # clock $end
$var wire 1 $ reset $end
$var wire 1 % t $end
$var wire 1 & x0 $end
$var wire 1 ' x1 $end
$var wire 1 ( x2 $end
$var wire 4 ) q [3:0] $end
$scope module T0 $end
$var wire 1 # clk $end
$var wire 1 $ reset $end
$var wire 1 % t $end
$var reg 1 * q $end
$upscope $end
$scope module T1 $end
$var wire 1 # clk $end
$var wire 1 $ reset $end
$var wire 1 & t $end
$var reg 1 + q $end
$upscope $end
$scope module T2 $end
$var wire 1 # clk $end
$var wire 1 $ reset $end
$var wire 1 ' t $end
$var reg 1 , q $end
$upscope $end
$scope module T3 $end
$var wire 1 # clk $end
$var wire 1 $ reset $end
$var wire 1 ( t $end
$var reg 1 - q $end
$upscope $end
$upscope $end
$upscope $end
$enddefinitions $end
#0
$dumpvars
0-
0,
0+
0*
b0 )
0(
0'
0&
1%
1$
0#
1"
b0 !
$end
#5
1&
b1 !
b1 )
1*
1#
0$
#10
0#
#15
0&
0*
b10 !
b10 )
1+
1#
#20
0#
#25
1'
1&
b11 !
b11 )
1*
1#
#30
0#
#35
0'
0&
0*
0+
b100 !
b100 )
1,
1#
#40
0#
#45
1&
b101 !
b101 )
1*
1#
#50
0#
#55
0&
0*
b110 !
b110 )
1+
1#
#60
0#
#65
1(
1'
1&
b111 !
b111 )
1*
1#
#70
0#
#75
0(
0'
0&
0*
0+
0,
b1000 !
b1000 )
1-
1#
#80
0#
#85
1&
b1001 !
b1001 )
1*
1#
#90
0#
#95
0&
0*
b1010 !
b1010 )
1+
1#
#100
0#
#105
1'
1&
b1011 !
b1011 )
1*
1#
#110
0#
#115
0'
0&
0*
0+
b1100 !
b1100 )
1,
1#
#120
0#
#125
1&
b1101 !
b1101 )
1*
1#
#130
0#
#135
0&
0*
b1110 !
b1110 )
1+
1#
#140
0#
#145
1(
1'
1&
b1111 !
b1111 )
1*
1#
#150
0&
0'
0(
0#
0"
#155
1&
b1110 !
b1110 )
0*
1#
#160
0#
#165
0&
0+
b1101 !
b1101 )
1*
1#
#170
0#
#175
1'
1&
b1100 !
b1100 )
0*
1#
#180
0#
#185
0'
0&
0,
1+
b1011 !
b1011 )
1*
1#
#190
0#
#195
1&
b1010 !
b1010 )
0*
1#
#200
0#
#205
0&
0+
b1001 !
b1001 )
1*
1#
#210
0#
#215
1(
1'
1&
b1000 !
b1000 )
0*
1#
#220
0#
#225
0(
0'
0&
0-
1,
1+
b111 !
b111 )
1*
1#
#230
0#
#235
1&
b110 !
b110 )
0*
1#
#240
0#
#245
0&
0+
b101 !
b101 )
1*
1#
#250
0#
#255
1'
1&
b100 !
b100 )
0*
1#
#260
0#
#265
0'
0&
0,
1+
b11 !
b11 )
1*
1#
#270
0#
#275
1&
b10 !
b10 )
0*
1#
#280
0#
#285
0&
0+
b1 !
b1 )
1*
1#
#290
0#
#295
1(
1'
1&
b0 !
b0 )
0*
1#
